pypiuma/__init__.py
pypiuma/core.py
pypiuma/templatetags/__init__.py
pypiuma/templatetags/pypiuma_tags.py
pypiuma-1.1.0.dist-info/LICENSE
pypiuma-1.1.0.dist-info/METADATA
pypiuma-1.1.0.dist-info/WHEEL
pypiuma-1.1.0.dist-info/top_level.txt
pypiuma-1.1.0.dist-info/RECORD
