Metadata-Version: 2.1
Name: pypiuma
Version: 1.1.0
Summary: Piuma Python library with Django support
Home-page: https://github.com/piumaio
Author: Lotrèk
Author-email: dimmitutto@lotrek.it
License: MIT
Platform: UNKNOWN
Classifier: Environment :: Web Environment
Classifier: Framework :: Django
Classifier: Intended Audience :: Developers
Classifier: Programming Language :: Python
Classifier: Programming Language :: Python :: 3
License-File: LICENSE
